types_watchpoints-0.2.5.20250822.dist-info/licenses/LICENSE
watchpoints-stubs/METADATA.toml
watchpoints-stubs/__init__.pyi
watchpoints-stubs/ast_monkey.pyi
watchpoints-stubs/py.typed
watchpoints-stubs/util.pyi
watchpoints-stubs/watch.pyi
watchpoints-stubs/watch_element.pyi
watchpoints-stubs/watch_print.pyi
types_watchpoints-0.2.5.20250822.dist-info/METADATA
types_watchpoints-0.2.5.20250822.dist-info/WHEEL
types_watchpoints-0.2.5.20250822.dist-info/top_level.txt
types_watchpoints-0.2.5.20250822.dist-info/RECORD
